{
  "arange": {
    "__compat__": {
      "__version_added__": "2021.12",
      "__description__": "Returns evenly spaced values within the half-open interval [start, stop) as a one-dimensional array.",
      "__spec_url__": "https://data-apis.org/array-api/latest/API_specification/generated/array_api.arange.html",
      "__support__": {
        "cupy": [
          {
            "version_added": "10.0.0",
            "status": {
              "experimental": true,
              "deprecated": false,
              "partial_implementation": false
            },
            "notes": "Provisionally available via `cupy.array_api`."
          }
        ],
        "dask": null,
        "jax": null,
        "mxnet": null,
        "numpy": [
          {
            "version_added": "1.22.0",
            "status": {
              "experimental": true,
              "deprecated": false,
              "partial_implementation": false
            },
            "notes": "Provisionally available via `numpy.array_api`."
          }
        ],
        "pytorch": null,
        "tensorflow": null
      },
      "__status__": {
        "standard_track": true,
        "experimental": false,
        "deprecated": false
      }
    },
    "start": {
      "__compat__": {
        "__version_added__": "2021.12",
        "__description__": "If stop is specified, the start of interval (inclusive); otherwise, the end of the interval (exclusive).",
        "__support__": {
          "cupy": [
            {
              "version_added": "10.0.0",
              "status": {
                "experimental": false,
                "deprecated": false,
                "partial_implementation": false
              },
              "notes": ""
            }
          ],
          "dask": null,
          "jax": null,
          "mxnet": null,
          "numpy": [
            {
              "version_added": "1.22.0",
              "status": {
                "experimental": false,
                "deprecated": false,
                "partial_implementation": false
              },
              "notes": ""
            }
          ],
          "pytorch": null,
          "tensorflow": null
        }
      },
      "__status__": {
        "standard_track": true,
        "experimental": false,
        "deprecated": false
      }
    },
    "stop": {
      "__compat__": {
        "__version_added__": "2021.12",
        "__description__": "The end of the interval.",
        "__support__": {
          "cupy": [
            {
              "version_added": "10.0.0",
              "status": {
                "experimental": false,
                "deprecated": false,
                "partial_implementation": false
              },
              "notes": ""
            }
          ],
          "dask": null,
          "jax": null,
          "mxnet": null,
          "numpy": [
            {
              "version_added": "1.22.0",
              "status": {
                "experimental": false,
                "deprecated": false,
                "partial_implementation": false
              },
              "notes": ""
            }
          ],
          "pytorch": null,
          "tensorflow": null
        }
      },
      "__status__": {
        "standard_track": true,
        "experimental": false,
        "deprecated": false
      }
    },
    "step": {
      "__compat__": {
        "__version_added__": "2021.12",
        "__description__": "The distance between two adjacent elements (out[i+1] - out[i]).",
        "__support__": {
          "cupy": [
            {
              "version_added": "10.0.0",
              "status": {
                "experimental": false,
                "deprecated": false,
                "partial_implementation": false
              },
              "notes": ""
            }
          ],
          "dask": null,
          "jax": null,
          "mxnet": null,
          "numpy": [
            {
              "version_added": "1.22.0",
              "status": {
                "experimental": false,
                "deprecated": false,
                "partial_implementation": false
              },
              "notes": ""
            }
          ],
          "pytorch": null,
          "tensorflow": null
        }
      },
      "__status__": {
        "standard_track": true,
        "experimental": false,
        "deprecated": false
      }
    },
    "dtype": {
      "__compat__": {
        "__version_added__": "2021.12",
        "__description__": "Output array data type.",
        "__support__": {
          "cupy": [
            {
              "version_added": "10.0.0",
              "status": {
                "experimental": false,
                "deprecated": false,
                "partial_implementation": false
              },
              "notes": ""
            }
          ],
          "dask": null,
          "jax": null,
          "mxnet": null,
          "numpy": [
            {
              "version_added": "1.22.0",
              "status": {
                "experimental": false,
                "deprecated": false,
                "partial_implementation": false
              },
              "notes": ""
            }
          ],
          "pytorch": null,
          "tensorflow": null
        }
      },
      "__status__": {
        "standard_track": true,
        "experimental": false,
        "deprecated": false
      }
    },
    "device": {
      "__compat__": {
        "__version_added__": "2021.12",
        "__description__": "Device on which to place the created array.",
        "__support__": {
          "cupy": [
            {
              "version_added": "10.0.0",
              "status": {
                "experimental": false,
                "deprecated": false,
                "partial_implementation": false
              },
              "notes": ""
            }
          ],
          "dask": null,
          "jax": null,
          "mxnet": null,
          "numpy": [
            {
              "version_added": "1.22.0",
              "status": {
                "experimental": false,
                "deprecated": false,
                "partial_implementation": false
              },
              "notes": ""
            }
          ],
          "pytorch": null,
          "tensorflow": null
        }
      },
      "__status__": {
        "standard_track": true,
        "experimental": false,
        "deprecated": false
      }
    }
  }
}
